twith.py
twith-1.0.dist-info/LICENSE
twith-1.0.dist-info/METADATA
twith-1.0.dist-info/WHEEL
twith-1.0.dist-info/top_level.txt
twith-1.0.dist-info/RECORD
