Metadata-Version: 2.1
Name: twith
Version: 1.0
Summary: Turn long text into a thread on Twitter.
Home-page: https://github.com/nxgeo/twith
Author: Nikolaus Georgi
License: UNKNOWN
Platform: UNKNOWN
Classifier: Development Status :: 5 - Production/Stable
Classifier: License :: OSI Approved :: MIT License
Requires-Python: >=3.6
License-File: LICENSE
Requires-Dist: requests-oauthlib
